LICENSE
MANIFEST.in
README.md
requirements.txt
setup.cfg
setup.py
gcdt_datadog_integration/__init__.py
gcdt_datadog_integration/datadog_notification.py
gcdt_datadog_integration.egg-info/PKG-INFO
gcdt_datadog_integration.egg-info/SOURCES.txt
gcdt_datadog_integration.egg-info/dependency_links.txt
gcdt_datadog_integration.egg-info/entry_points.txt
gcdt_datadog_integration.egg-info/requires.txt
gcdt_datadog_integration.egg-info/top_level.txt